{
  "version": 1,
  "skills": {
    "github": {
      "version": "1.0.0",
      "installedAt": 1770213971121
    },
    "github-pr": {
      "version": "1.0.0",
      "installedAt": 1770213974061
    },
    "pr-reviewer": {
      "version": "1.0.0",
      "installedAt": 1770213976729
    },
    "clawdex": {
      "version": "1.0.2",
      "installedAt": 1770214772760
    },
    "crypto-wallet": {
      "version": "1.0.1",
      "installedAt": 1770214781877
    },
    "base-trader": {
      "version": "1.1.1",
      "installedAt": 1770214785421
    },
    "crypto-agent-payments": {
      "version": "0.1.7",
      "installedAt": 1770214787841
    },
    "x-twitter": {
      "version": "2.3.1",
      "installedAt": 1770214796716
    },
    "social-card-gen": {
      "version": "1.0.2",
      "installedAt": 1770214799287
    },
    "ai-landing": {
      "version": "1.0.1",
      "installedAt": 1770214957145
    },
    "web-deploy-github": {
      "version": "1.0.0",
      "installedAt": 1770214960542
    },
    "ai-code-review": {
      "version": "1.0.1",
      "installedAt": 1770215068275
    },
    "secret-scanner": {
      "version": "1.0.1",
      "installedAt": 1770215071548
    }
  }
}
